quantreo/__init__.py
quantreo/data_aggregation/__init__.py
quantreo/data_aggregation/bar_building/__init__.py
quantreo/data_aggregation/bar_building/tick_bars.py
quantreo/data_aggregation/bar_building/tick_imbalance_bars.py
quantreo/data_aggregation/bar_building/time_bars.py
quantreo/data_aggregation/bar_building/volume_bars.py
quantreo/data_aggregation/bar_building/volume_imbalance_bars.py
quantreo/data_aggregation/bar_metrics/__init__.py
quantreo/data_aggregation/bar_metrics/distribution.py
quantreo/data_aggregation/bar_metrics/volume.py
quantreo/datasets/__init__.py
quantreo/datasets/generated_ohlcv.csv
quantreo/datasets/generated_ohlcv_with_time.csv
quantreo/datasets/generated_ticks.csv
quantreo/features_engineering/__init__.py
quantreo/features_engineering/candle/__init__.py
quantreo/features_engineering/candle/distribution.py
quantreo/features_engineering/candle/info.py
quantreo/features_engineering/candle/position.py
quantreo/features_engineering/candle/ranges.py
quantreo/features_engineering/market_regime/__init__.py
quantreo/features_engineering/market_regime/trendiness.py
quantreo/features_engineering/math/__init__.py
quantreo/features_engineering/math/correlation.py
quantreo/features_engineering/math/distribution.py
quantreo/features_engineering/math/entropy.py
quantreo/features_engineering/math/fractal.py
quantreo/features_engineering/math/operators.py
quantreo/features_engineering/math/statistical_tests.py
quantreo/features_engineering/transformation/__init__.py
quantreo/features_engineering/transformation/filters.py
quantreo/features_engineering/transformation/fourier.py
quantreo/features_engineering/transformation/non_linear.py
quantreo/features_engineering/transformation/smoothing.py
quantreo/features_engineering/transformation/wavelet.py
quantreo/features_engineering/trend/__init__.py
quantreo/features_engineering/trend/moving_averages.py
quantreo/features_engineering/trend/slopes.py
quantreo/features_engineering/volatility/__init__.py
quantreo-0.0.30.dist-info/licenses/LICENSE.txt
quantreo-0.0.30.dist-info/METADATA
quantreo-0.0.30.dist-info/WHEEL
quantreo-0.0.30.dist-info/top_level.txt
quantreo-0.0.30.dist-info/RECORD
