Metadata-Version: 2.4
Name: quantreo
Version: 0.0.30
Summary: Python library for quantitative trading
Home-page: https://github.com/Quantreo/quantreo
Author: Lucas Inglese
Author-email: lucas@quantreo.com
Classifier: Development Status :: 3 - Alpha
Classifier: Intended Audience :: Developers
Classifier: License :: OSI Approved :: MIT License
Classifier: Programming Language :: Python :: 3.11
License-File: LICENSE.txt
Requires-Dist: tqdm
Requires-Dist: numpy
Requires-Dist: pandas
Requires-Dist: numba
Requires-Dist: scipy
Requires-Dist: PyWavelets
Requires-Dist: antropy>=0.1.9
Dynamic: author
Dynamic: author-email
Dynamic: classifier
Dynamic: description
Dynamic: description-content-type
Dynamic: home-page
Dynamic: license-file
Dynamic: requires-dist
Dynamic: summary
